code2md/__init__.py
code2md/__main__.py
code2md/main.py
code2md-1.0.0.dist-info/licenses/LICENSE
code2md-1.0.0.dist-info/METADATA
code2md-1.0.0.dist-info/WHEEL
code2md-1.0.0.dist-info/entry_points.txt
code2md-1.0.0.dist-info/top_level.txt
code2md-1.0.0.dist-info/RECORD
