Metadata-Version: 2.4
Name: code2md
Version: 1.0.0
Summary: Convert code directory structure and contents to markdown
Author-email: George Holt <georgeholt77@googlemail.com>
License: MIT
Project-URL: Homepage, https://pypi.org/project/code2md/
Project-URL: Source, https://github.com/georgeholt1/code2md
Classifier: Intended Audience :: Developers
Classifier: License :: OSI Approved :: MIT License
Classifier: Operating System :: OS Independent
Classifier: Programming Language :: Python :: 3
Classifier: Programming Language :: Python :: 3.7
Classifier: Programming Language :: Python :: 3.8
Classifier: Programming Language :: Python :: 3.9
Classifier: Programming Language :: Python :: 3.10
Classifier: Programming Language :: Python :: 3.11
Requires-Python: >=3.7
License-File: LICENSE
Requires-Dist: pyyaml
Provides-Extra: dev
Requires-Dist: build; extra == "dev"
Requires-Dist: twine; extra == "dev"
Requires-Dist: pre-commit; extra == "dev"
Requires-Dist: black==25.1; extra == "dev"
Requires-Dist: isort==5.13; extra == "dev"
Dynamic: license-file
